{"is_source_file": false, "format": "", "description": "", "external_files": [], "external_methods": [], "published": [], "classes": [], "methods": [], "calls": [], "search-terms": [], "state": 2, "file_id": 27, "knowledge_revision": 36, "git_revision": "216ef7ad703619aecf37ad82a95792a5439a5527", "hash": "d2b40d02d5f7873d8a6713bad837edd4", "format-version": 4, "code-base-name": "calory_app_frontend", "filename": "calory_app_frontend/public/index.html", "revision_history": [{"36": "216ef7ad703619aecf37ad82a95792a5439a5527"}]}